{
  "nightly": {
    "description": "Every commit to develop",
    "hide": false,
    "last_updated": "2024-10-02T00:34:56.000Z",
    "last_updated_url": "https://github.com/hotio/qbitmanage/actions/runs/11135669464",
    "latest": false,
    "tags": [
      "nightly",
      "nightly-0e75b4cda173d631c20ddc27aedf4f117c414efe",
      "nightly-7d8f587"
    ]
  },
  "release": {
    "description": "Releases",
    "hide": false,
    "last_updated": "2024-09-25T05:25:53.000Z",
    "last_updated_url": "https://github.com/hotio/qbitmanage/actions/runs/11026718032",
    "latest": true,
    "tags": [
      "release",
      "release-4.1.9",
      "release-442f353"
    ]
  }
}
