{
  "nightly": {
    "description": "Every commit to develop",
    "hide": false,
    "last_updated": "2025-07-13T18:36:30.000Z",
    "last_updated_url": "https://github.com/hotio/qbitmanage/actions/runs/16252216724",
    "latest": false,
    "tags": [
      "nightly",
      "nightly-4bedd5d3e48903a518afacff7301e7384556bd8c",
      "nightly-6b5cc78"
    ]
  },
  "release": {
    "description": "Releases",
    "hide": false,
    "last_updated": "2025-07-11T23:33:17.000Z",
    "last_updated_url": "https://github.com/hotio/qbitmanage/actions/runs/16231623127",
    "latest": true,
    "tags": [
      "release",
      "release-4.5.0",
      "release-6bb309c"
    ]
  }
}
