{
  "nightly": {
    "description": "Every commit to develop",
    "hide": false,
    "last_updated": "2025-03-14T00:52:08.000Z",
    "last_updated_url": "https://github.com/hotio/qbitmanage/actions/runs/13847517670",
    "latest": false,
    "tags": [
      "nightly",
      "nightly-d72fa7085d9594a97f3498183d9175534a3d95ec",
      "nightly-37f4530"
    ]
  },
  "release": {
    "description": "Releases",
    "hide": false,
    "last_updated": "2025-03-01T02:23:23.000Z",
    "last_updated_url": "https://github.com/hotio/qbitmanage/actions/runs/13600010472",
    "latest": true,
    "tags": [
      "release",
      "release-4.2.0",
      "release-e048474"
    ]
  }
}
