{
  "nightly": {
    "description": "Every commit to develop",
    "hide": false,
    "last_updated": "2024-02-11T20:46:12.000Z",
    "last_updated_url": "https://github.com/hotio/qbitmanage/actions/runs/7864559862",
    "latest": false,
    "tags": [
      "nightly",
      "nightly-42baacdadcc68c86c2b3ed3899fec1e893993976",
      "nightly-44445c8"
    ]
  },
  "release": {
    "description": "Releases",
    "hide": false,
    "last_updated": "2024-02-09T05:20:01.000Z",
    "last_updated_url": "https://github.com/hotio/qbitmanage/actions/runs/7839893667",
    "latest": true,
    "tags": [
      "release",
      "release-4.0.8",
      "release-bf9fdf4"
    ]
  }
}
